hammadpy/__init__.py
hammadpy/core.py
hammadpy/lightspeed.py
hammadpy/modules/__init__.py
hammadpy/modules/inputs.py
hammadpy/modules/loaders.py
hammadpy/modules/text.py
hammadpy-3.10.1.dist-info/METADATA
hammadpy-3.10.1.dist-info/WHEEL
hammadpy-3.10.1.dist-info/top_level.txt
hammadpy-3.10.1.dist-info/RECORD
