Metadata-Version: 2.1
Name: hammadpy
Version: 3.10.1
Summary: Hammad's Accelarated Micro Modules for Application Development (Hammad's Python Library)
Author: Hammad Saeed
Author-email: hammad@supportvectors.com
Classifier: Programming Language :: Python :: 3
Classifier: License :: OSI Approved :: MIT License
Classifier: Operating System :: OS Independent
Requires-Python: >3.9
Requires-Dist: art
Requires-Dist: libhammadpy-text
Requires-Dist: prompt-toolkit
Requires-Dist: wcwidth
